mojo/startup/__init__.py
mojo/startup/converters.py
mojo/startup/presencesettings.py
mojo/startup/presencevariables.py
mojo/startup/startupconfigloader.py
mojo/startup/startupdefaults.py
mojo/startup/startupvariables.py
mojo/startup/wellknown.py
mojo_startup-2.0.7.dist-info/LICENSE.txt
mojo_startup-2.0.7.dist-info/METADATA
mojo_startup-2.0.7.dist-info/WHEEL
mojo_startup-2.0.7.dist-info/RECORD
