Metadata-Version: 2.1
Name: mojo-startup
Version: 2.0.7
Summary: Automation Mojo Startup Package
License: LICENSE.txt
Keywords: python
Author: Myron W. Walker
Requires-Python: >=3.9,<4.0
Classifier: License :: OSI Approved :: MIT License
Classifier: License :: Other/Proprietary License
Classifier: Operating System :: POSIX
Classifier: Programming Language :: Python :: 3
Classifier: Programming Language :: Python :: 3.9
Classifier: Programming Language :: Python :: 3.10
Classifier: Programming Language :: Python :: 3.11
Classifier: Programming Language :: Python :: 3.12
Requires-Dist: mojo-collections (>=2.0.1,<2.1.0)
Requires-Dist: typing-extensions (>=4.11.0,<5.0.0)
